piqel-0.202208.0.dist-info/METADATA
piqel-0.202208.0.dist-info/WHEEL
piqel/__init__.py
piqel/__pycache__/__init__.cpython-310.pyc
piqel/piqel.cpython-310-darwin.so
piqel-0.202208.0.dist-info/RECORD
