Metadata-Version: 2.1
Name: piqel
Version: 0.202208.0
Summary: A implementation of PartiQL
Keywords: PartiQL SQL
Home-Page: https://github.com/fuyutarow/piqel
Author: FUKUDA Yutaro <fuyutarow@gmail.com>
Author-Email: FUKUDA Yutaro <fuyutarow@gmail.com>
License: MIT
